keras_resnet/__init__.py
keras_resnet/block.py
keras_resnet/model.py
keras_resnet-0.0.1.dist-info/DESCRIPTION.rst
keras_resnet-0.0.1.dist-info/METADATA
keras_resnet-0.0.1.dist-info/RECORD
keras_resnet-0.0.1.dist-info/WHEEL
keras_resnet-0.0.1.dist-info/metadata.json
keras_resnet-0.0.1.dist-info/top_level.txt
