Metadata-Version: 2.0
Name: keras-resnet
Version: 0.0.1
Summary: UNKNOWN
Home-page: https://github.com/0x00b1/keras-resnet
Author: Allen Goodman
Author-email: allen.goodman@icloud.com
License: MIT
Platform: UNKNOWN
Requires-Dist: keras
